{
  "predictions": [
    {
      "ticker": "ADANIENT.NS",
      "prediction_date": "2026-01-12",
      "target_date": "2026-01-13",
      "models": {
        "baseline": {
          "current_price": 2153.699951171875,
          "predicted_price": 2245.09149614349,
          "predicted_change": 91.39154497161508,
          "predicted_change_pct": 4.243466919423344,
          "predicted_direction": 1,
          "confidence": 0.5
        },
        "mslstm": {
          "current_price": 2153.699951171875,
          "predicted_price": 2255.157122772187,
          "predicted_change": 101.457171600312,
          "predicted_change_pct": 4.710831308934504,
          "predicted_direction": 1,
          "confidence": 0.5
        },
        "mslstma": {
          "current_price": 2153.699951171875,
          "predicted_price": 2222.4673069436103,
          "predicted_change": 68.76735577173531,
          "predicted_change_pct": 3.192986828751021,
          "predicted_direction": 1,
          "confidence": 0.5
        },
        "ensemble": {
          "current_price": 2153.699951171875,
          "predicted_price": 2154.524130451642,
          "predicted_change": 0.8241792797671224,
          "predicted_change_pct": 0.03826806418965045,
          "predicted_direction": 1,
          "confidence": 0.02856087150606168
        }
      }
    },
    {
      "ticker": "ADANIGREEN.NS",
      "prediction_date": "2026-01-12",
      "target_date": "2026-01-13",
      "models": {
        "baseline": {
          "current_price": 946.0999755859375,
          "predicted_price": 1030.649044486654,
          "predicted_change": 84.54906890071652,
          "predicted_change_pct": 8.936589269897578,
          "predicted_direction": 1,
          "confidence": 0.5
        },
        "mslstm": {
          "current_price": 946.0999755859375,
          "predicted_price": 985.9828639738317,
          "predicted_change": 39.88288838789424,
          "predicted_change_pct": 4.215504641905743,
          "predicted_direction": 1,
          "confidence": 0.5
        },
        "mslstma": {
          "current_price": 946.0999755859375,
          "predicted_price": 976.3159140777317,
          "predicted_change": 30.21593849179419,
          "predicted_change_pct": 3.193736314503215,
          "predicted_direction": 1,
          "confidence": 0.5
        },
        "ensemble": {
          "current_price": 946.0999755859375,
          "predicted_price": 941.3132185594869,
          "predicted_change": -4.786757026450573,
          "predicted_change_pct": -0.5059462160419193,
          "predicted_direction": 0,
          "confidence": 0.2723605619985674
        }
      }
    },
    {
      "ticker": "ADANIPORTS.NS",
      "prediction_date": "2026-01-12",
      "target_date": "2026-01-13",
      "models": {
        "baseline": {
          "current_price": 1435.9000244140625,
          "predicted_price": 1440.7412295990944,
          "predicted_change": 4.841205185031868,
          "predicted_change_pct": 0.3371547533058461,
          "predicted_direction": 1,
          "confidence": 0.5
        },
        "mslstm": {
          "current_price": 1435.9000244140625,
          "predicted_price": 1491.5739248552563,
          "predicted_change": 55.67390044119384,
          "predicted_change_pct": 3.877282505368873,
          "predicted_direction": 1,
          "confidence": 0.5
        },
        "mslstma": {
          "current_price": 1435.9000244140625,
          "predicted_price": 1435.3029802234523,
          "predicted_change": -0.5970441906101769,
          "predicted_change_pct": -0.04157978831804687,
          "predicted_direction": 0,
          "confidence": 0.5
        },
        "ensemble": {
          "current_price": 1435.9000244140625,
          "predicted_price": 1438.8223115515593,
          "predicted_change": 2.9222871374968236,
          "predicted_change_pct": 0.2035160587652518,
          "predicted_direction": 1,
          "confidence": 0.14751430066300775
        }
      }
    },
    {
      "ticker": "APOLLOHOSP.NS",
      "prediction_date": "2026-01-12",
      "target_date": "2026-01-13",
      "models": {
        "baseline": {
          "current_price": 7256.5,
          "predicted_price": 6953.714244862087,
          "predicted_change": -302.78575513791293,
          "predicted_change_pct": -4.172614278755782,
          "predicted_direction": 0,
          "confidence": 0.5
        },
        "mslstm": {
          "current_price": 7256.5,
          "predicted_price": 7163.811700265738,
          "predicted_change": -92.68829973426182,
          "predicted_change_pct": -1.2773141284953105,
          "predicted_direction": 0,
          "confidence": 0.5
        },
        "mslstma": {
          "current_price": 7256.5,
          "predicted_price": 6963.091645848472,
          "predicted_change": -293.40835415152833,
          "predicted_change_pct": -4.043386676104577,
          "predicted_direction": 0,
          "confidence": 0.5
        },
        "ensemble": {
          "current_price": 7256.5,
          "predicted_price": 7295.696572398555,
          "predicted_change": 39.19657239855496,
          "predicted_change_pct": 0.5401580982368204,
          "predicted_direction": 1,
          "confidence": 0.3131489249321393
        }
      }
    },
    {
      "ticker": "AXISBANK.NS",
      "prediction_date": "2026-01-12",
      "target_date": "2026-01-13",
      "models": {
        "baseline": {
          "current_price": 1272.0,
          "predicted_price": 1268.2761232511364,
          "predicted_change": -3.7238767488636313,
          "predicted_change_pct": -0.29275760604273726,
          "predicted_direction": 0,
          "confidence": 0.5
        },
        "mslstm": {
          "current_price": 1272.0,
          "predicted_price": 1259.6371232117415,
          "predicted_change": -12.362876788258518,
          "predicted_change_pct": -0.9719242758064905,
          "predicted_direction": 0,
          "confidence": 0.5
        },
        "mslstma": {
          "current_price": 1272.0,
          "predicted_price": 1277.3734748365239,
          "predicted_change": 5.373474836523883,
          "predicted_change_pct": 0.42244299029274845,
          "predicted_direction": 1,
          "confidence": 0.5
        },
        "ensemble": {
          "current_price": 1272.0,
          "predicted_price": 1269.740124333722,
          "predicted_change": -2.259875666278049,
          "predicted_change_pct": -0.17766318131117176,
          "predicted_direction": 0,
          "confidence": 0.08979040191608634
        }
      }
    },
    {
      "ticker": "BAJAJ-AUTO.NS",
      "prediction_date": "2026-01-12",
      "target_date": "2026-01-13",
      "models": {
        "baseline": {
          "current_price": 9562.5,
          "predicted_price": 9343.670224581903,
          "predicted_change": -218.8297754180967,
          "predicted_change_pct": -2.288415952084666,
          "predicted_direction": 0,
          "confidence": 0.5
        },
        "mslstm": {
          "current_price": 9562.5,
          "predicted_price": 9399.029434872122,
          "predicted_change": -163.47056512787822,
          "predicted_change_pct": -1.7094961059124558,
          "predicted_direction": 0,
          "confidence": 0.5
        },
        "mslstma": {
          "current_price": 9562.5,
          "predicted_price": 9659.636449613085,
          "predicted_change": 97.13644961308455,
          "predicted_change_pct": 1.0158060090257104,
          "predicted_direction": 1,
          "confidence": 0.5
        },
        "ensemble": {
          "current_price": 9562.5,
          "predicted_price": 9436.51080345652,
          "predicted_change": -125.98919654347992,
          "predicted_change_pct": -1.3175340815004488,
          "predicted_direction": 0,
          "confidence": 0.4657659771771623
        }
      }
    },
    {
      "ticker": "BRITANNIA.NS",
      "prediction_date": "2026-01-12",
      "target_date": "2026-01-13",
      "models": {
        "baseline": {
          "current_price": 5977.5,
          "predicted_price": 5887.632025288069,
          "predicted_change": -89.86797471193131,
          "predicted_change_pct": -1.5034374690410912,
          "predicted_direction": 0,
          "confidence": 0.5
        },
        "mslstm": {
          "current_price": 5977.5,
          "predicted_price": 5913.792420722777,
          "predicted_change": -63.707579277222976,
          "predicted_change_pct": -1.0657896993261917,
          "predicted_direction": 0,
          "confidence": 0.5
        },
        "mslstma": {
          "current_price": 5977.5,
          "predicted_price": 5892.406903987896,
          "predicted_change": -85.09309601210407,
          "predicted_change_pct": -1.423556604133902,
          "predicted_direction": 0,
          "confidence": 0.5
        },
        "ensemble": {
          "current_price": 5977.5,
          "predicted_price": 5965.802655770489,
          "predicted_change": -11.697344229511145,
          "predicted_change_pct": -0.19568957305748924,
          "predicted_direction": 0,
          "confidence": 0.11588050557268481
        }
      }
    },
    {
      "ticker": "CIPLA.NS",
      "prediction_date": "2026-01-12",
      "target_date": "2026-01-13",
      "models": {
        "baseline": {
          "current_price": 1465.699951171875,
          "predicted_price": 1486.1914982721646,
          "predicted_change": 20.49154710028961,
          "predicted_change_pct": 1.3980724420374013,
          "predicted_direction": 1,
          "confidence": 0.5
        },
        "mslstm": {
          "current_price": 1465.699951171875,
          "predicted_price": 1505.5619553340075,
          "predicted_change": 39.86200416213251,
          "predicted_change_pct": 2.719656511570556,
          "predicted_direction": 1,
          "confidence": 0.5
        },
        "mslstma": {
          "current_price": 1465.699951171875,
          "predicted_price": 1497.332320364294,
          "predicted_change": 31.63236919241899,
          "predicted_change_pct": 2.1581749502773695,
          "predicted_direction": 1,
          "confidence": 0.5
        },
        "ensemble": {
          "current_price": 1465.699951171875,
          "predicted_price": 1465.0357575152684,
          "predicted_change": -0.6641936566065851,
          "predicted_change_pct": -0.04531579987264722,
          "predicted_direction": 0,
          "confidence": 0.04123435238088269
        }
      }
    },
    {
      "ticker": "COALINDIA.NS",
      "prediction_date": "2026-01-12",
      "target_date": "2026-01-13",
      "models": {
        "baseline": {
          "current_price": 418.3500061035156,
          "predicted_price": 402.3252910238479,
          "predicted_change": -16.024715079667715,
          "predicted_change_pct": -3.8304565186746076,
          "predicted_direction": 0,
          "confidence": 0.5
        },
        "mslstm": {
          "current_price": 418.3500061035156,
          "predicted_price": 416.5493182808586,
          "predicted_change": -1.8006878226570393,
          "predicted_change_pct": -0.43042614948868296,
          "predicted_direction": 0,
          "confidence": 0.5
        },
        "mslstma": {
          "current_price": 418.3500061035156,
          "predicted_price": 412.53735246486934,
          "predicted_change": -5.812653638646282,
          "predicted_change_pct": -1.3894235816523492,
          "predicted_direction": 0,
          "confidence": 0.5
        },
        "ensemble": {
          "current_price": 418.3500061035156,
          "predicted_price": 407.9048049852287,
          "predicted_change": -10.445201118286946,
          "predicted_change_pct": -2.4967613160981728,
          "predicted_direction": 0,
          "confidence": 0.5633524134396265
        }
      }
    },
    {
      "ticker": "DABUR.NS",
      "prediction_date": "2026-01-12",
      "target_date": "2026-01-13",
      "models": {
        "baseline": {
          "current_price": 522.4000244140625,
          "predicted_price": 500.4807135440496,
          "predicted_change": -21.919310870012907,
          "predicted_change_pct": -4.195886264476767,
          "predicted_direction": 0,
          "confidence": 0.5
        },
        "mslstm": {
          "current_price": 522.4000244140625,
          "predicted_price": 498.92503174190637,
          "predicted_change": -23.474992672156134,
          "predicted_change_pct": -4.493681388795167,
          "predicted_direction": 0,
          "confidence": 0.5
        },
        "mslstma": {
          "current_price": 522.4000244140625,
          "predicted_price": 506.20633908063877,
          "predicted_change": -16.19368533342373,
          "predicted_change_pct": -3.099863050654905,
          "predicted_direction": 0,
          "confidence": 0.5
        },
        "ensemble": {
          "current_price": 522.4000244140625,
          "predicted_price": 517.4418594966921,
          "predicted_change": -4.958164917370368,
          "predicted_change_pct": -0.9491126886779111,
          "predicted_direction": 0,
          "confidence": 0.43563052525102686
        }
      }
    },
    {
      "ticker": "DIVISLAB.NS",
      "prediction_date": "2026-01-12",
      "target_date": "2026-01-13",
      "models": {
        "baseline": {
          "current_price": 6616.5,
          "predicted_price": 6463.168312087655,
          "predicted_change": -153.33168791234493,
          "predicted_change_pct": -2.317413857966366,
          "predicted_direction": 0,
          "confidence": 0.5
        },
        "mslstm": {
          "current_price": 6616.5,
          "predicted_price": 6289.465827381238,
          "predicted_change": -327.03417261876166,
          "predicted_change_pct": -4.9427064553579925,
          "predicted_direction": 0,
          "confidence": 0.5
        },
        "mslstma": {
          "current_price": 6616.5,
          "predicted_price": 6344.727784188464,
          "predicted_change": -271.7722158115357,
          "predicted_change_pct": -4.107492115340971,
          "predicted_direction": 0,
          "confidence": 0.5
        },
        "ensemble": {
          "current_price": 6616.5,
          "predicted_price": 6597.380078129847,
          "predicted_change": -19.11992187015312,
          "predicted_change_pct": -0.2889733525300864,
          "predicted_direction": 0,
          "confidence": 0.19130977559234963
        }
      }
    },
    {
      "ticker": "DRREDDY.NS",
      "prediction_date": "2026-01-12",
      "target_date": "2026-01-13",
      "models": {
        "baseline": {
          "current_price": 1210.0999755859375,
          "predicted_price": 1236.7986220343955,
          "predicted_change": 26.69864644845802,
          "predicted_change_pct": 2.2063174107189276,
          "predicted_direction": 1,
          "confidence": 0.5
        },
        "mslstm": {
          "current_price": 1210.0999755859375,
          "predicted_price": 1205.550326676741,
          "predicted_change": -4.549648909196549,
          "predicted_change_pct": -0.37597297752143266,
          "predicted_direction": 0,
          "confidence": 0.5
        },
        "mslstma": {
          "current_price": 1210.0999755859375,
          "predicted_price": 1220.5165390801194,
          "predicted_change": 10.4165634941819,
          "predicted_change_pct": 0.8608018927641181,
          "predicted_direction": 1,
          "confidence": 0.5
        },
        "ensemble": {
          "current_price": 1210.0999755859375,
          "predicted_price": 1206.816274978464,
          "predicted_change": -3.28370060747352,
          "predicted_change_pct": -0.27135779470481847,
          "predicted_direction": 0,
          "confidence": 0.18394405715491968
        }
      }
    },
    {
      "ticker": "GRASIM.NS",
      "prediction_date": "2026-01-12",
      "target_date": "2026-01-13",
      "models": {
        "baseline": {
          "current_price": 2776.89990234375,
          "predicted_price": 2735.766271498622,
          "predicted_change": -41.13363084512821,
          "predicted_change_pct": -1.4812788466163518,
          "predicted_direction": 0,
          "confidence": 0.5
        },
        "mslstm": {
          "current_price": 2776.89990234375,
          "predicted_price": 2719.0359944106895,
          "predicted_change": -57.863907933060545,
          "predicted_change_pct": -2.0837592267629934,
          "predicted_direction": 0,
          "confidence": 0.5
        },
        "mslstma": {
          "current_price": 2776.89990234375,
          "predicted_price": 2688.15862654199,
          "predicted_change": -88.74127580175991,
          "predicted_change_pct": -3.195695881110472,
          "predicted_direction": 0,
          "confidence": 0.5
        },
        "ensemble": {
          "current_price": 2776.89990234375,
          "predicted_price": 2790.6619779663592,
          "predicted_change": 13.762075622609245,
          "predicted_change_pct": 0.4955913467026285,
          "predicted_direction": 1,
          "confidence": 0.3230593352565694
        }
      }
    },
    {
      "ticker": "HCLTECH.NS",
      "prediction_date": "2026-01-12",
      "target_date": "2026-01-13",
      "models": {
        "baseline": {
          "current_price": 1661.4000244140625,
          "predicted_price": 1624.1721370596642,
          "predicted_change": -37.22788735439826,
          "predicted_change_pct": -2.24075399105208,
          "predicted_direction": 0,
          "confidence": 0.5
        },
        "mslstm": {
          "current_price": 1661.4000244140625,
          "predicted_price": 1640.890634170566,
          "predicted_change": -20.509390243496455,
          "predicted_change_pct": -1.23446430372659,
          "predicted_direction": 0,
          "confidence": 0.5
        },
        "mslstma": {
          "current_price": 1661.4000244140625,
          "predicted_price": 1654.0096426843666,
          "predicted_change": -7.390381729695946,
          "predicted_change_pct": -0.4448285555010978,
          "predicted_direction": 0,
          "confidence": 0.5
        },
        "ensemble": {
          "current_price": 1661.4000244140625,
          "predicted_price": 1661.0415888748166,
          "predicted_change": -0.3584355392458747,
          "predicted_change_pct": -0.021574306848359814,
          "predicted_direction": 0,
          "confidence": 0.01666392830091623
        }
      }
    },
    {
      "ticker": "HDFCBANK.NS",
      "prediction_date": "2026-01-12",
      "target_date": "2026-01-13",
      "models": {
        "baseline": {
          "current_price": 939.0,
          "predicted_price": 985.1531505356361,
          "predicted_change": 46.15315053563609,
          "predicted_change_pct": 4.915138502197669,
          "predicted_direction": 1,
          "confidence": 0.5
        },
        "mslstm": {
          "current_price": 939.0,
          "predicted_price": 939.7691012617688,
          "predicted_change": 0.7691012617688102,
          "predicted_change_pct": 0.08190641765375428,
          "predicted_direction": 1,
          "confidence": 0.5
        },
        "mslstma": {
          "current_price": 939.0,
          "predicted_price": 951.3553343477324,
          "predicted_change": 12.355334347732423,
          "predicted_change_pct": 1.3157970551365805,
          "predicted_direction": 1,
          "confidence": 0.5
        },
        "ensemble": {
          "current_price": 939.0,
          "predicted_price": 936.2705199765102,
          "predicted_change": -2.7294800234898275,
          "predicted_change_pct": -0.2906794487209652,
          "predicted_direction": 0,
          "confidence": 0.17152942552685824
        }
      }
    },
    {
      "ticker": "HEROMOTOCO.NS",
      "prediction_date": "2026-01-12",
      "target_date": "2026-01-13",
      "models": {
        "baseline": {
          "current_price": 5773.0,
          "predicted_price": 5375.818221530819,
          "predicted_change": -397.18177846918115,
          "predicted_change_pct": -6.879989233833039,
          "predicted_direction": 0,
          "confidence": 0.5
        },
        "mslstm": {
          "current_price": 5773.0,
          "predicted_price": 5677.0222813473665,
          "predicted_change": -95.97771865263348,
          "predicted_change_pct": -1.6625276052768645,
          "predicted_direction": 0,
          "confidence": 0.5
        },
        "mslstma": {
          "current_price": 5773.0,
          "predicted_price": 5457.716709503962,
          "predicted_change": -315.2832904960378,
          "predicted_change_pct": -5.46134229163412,
          "predicted_direction": 0,
          "confidence": 0.5
        },
        "ensemble": {
          "current_price": 5773.0,
          "predicted_price": 5724.074448111704,
          "predicted_change": -48.92555188829556,
          "predicted_change_pct": -0.8474892064489148,
          "predicted_direction": 0,
          "confidence": 0.23732948624003558
        }
      }
    },
    {
      "ticker": "HINDALCO.NS",
      "prediction_date": "2026-01-12",
      "target_date": "2026-01-13",
      "models": {
        "baseline": {
          "current_price": 900.9500122070312,
          "predicted_price": 779.5512407994393,
          "predicted_change": -121.398771407592,
          "predicted_change_pct": -13.47452908183051,
          "predicted_direction": 0,
          "confidence": 0.5
        },
        "mslstm": {
          "current_price": 900.9500122070312,
          "predicted_price": 828.8373061234288,
          "predicted_change": -72.11270608360246,
          "predicted_change_pct": -8.004074044790787,
          "predicted_direction": 0,
          "confidence": 0.5
        },
        "mslstma": {
          "current_price": 900.9500122070312,
          "predicted_price": 807.4064687152877,
          "predicted_change": -93.54354349174355,
          "predicted_change_pct": -10.38276732607979,
          "predicted_direction": 0,
          "confidence": 0.5
        },
        "ensemble": {
          "current_price": 900.9500122070312,
          "predicted_price": 896.1118465040543,
          "predicted_change": -4.838165702976994,
          "predicted_change_pct": -0.5370071188661285,
          "predicted_direction": 0,
          "confidence": 0.1166867038924525
        }
      }
    },
    {
      "ticker": "HINDUNILVR.NS",
      "prediction_date": "2026-01-12",
      "target_date": "2026-01-13",
      "models": {
        "baseline": {
          "current_price": 2372.60009765625,
          "predicted_price": 2294.524833114483,
          "predicted_change": -78.07526454176696,
          "predicted_change_pct": -3.2907047681104307,
          "predicted_direction": 0,
          "confidence": 0.5
        },
        "mslstm": {
          "current_price": 2372.60009765625,
          "predicted_price": 2343.9407155382214,
          "predicted_change": -28.65938211802859,
          "predicted_change_pct": -1.207931422844477,
          "predicted_direction": 0,
          "confidence": 0.5
        },
        "mslstma": {
          "current_price": 2372.60009765625,
          "predicted_price": 2350.2740342586767,
          "predicted_change": -22.326063397573307,
          "predicted_change_pct": -0.9409956367964378,
          "predicted_direction": 0,
          "confidence": 0.5
        },
        "ensemble": {
          "current_price": 2372.60009765625,
          "predicted_price": 2326.800964300593,
          "predicted_change": -45.79913335565698,
          "predicted_change_pct": -1.930335137425776,
          "predicted_direction": 0,
          "confidence": 0.6978582973584591
        }
      }
    },
    {
      "ticker": "ICICIBANK.NS",
      "prediction_date": "2026-01-12",
      "target_date": "2026-01-13",
      "models": {
        "baseline": {
          "current_price": 1404.300048828125,
          "predicted_price": 1372.218590378194,
          "predicted_change": -32.081458449931006,
          "predicted_change_pct": -2.2845159392184455,
          "predicted_direction": 0,
          "confidence": 0.5
        },
        "mslstm": {
          "current_price": 1404.300048828125,
          "predicted_price": 1341.3980248912558,
          "predicted_change": -62.90202393686923,
          "predicted_change_pct": -4.479243875933802,
          "predicted_direction": 0,
          "confidence": 0.5
        },
        "mslstma": {
          "current_price": 1404.300048828125,
          "predicted_price": 1359.3881203430064,
          "predicted_change": -44.91192848511855,
          "predicted_change_pct": -3.198171823934426,
          "predicted_direction": 0,
          "confidence": 0.5
        },
        "ensemble": {
          "current_price": 1404.300048828125,
          "predicted_price": 1392.802851936269,
          "predicted_change": -11.497196891855992,
          "predicted_change_pct": -0.8187137002131584,
          "predicted_direction": 0,
          "confidence": 0.46617473635002304
        }
      }
    },
    {
      "ticker": "INFY.NS",
      "prediction_date": "2026-01-12",
      "target_date": "2026-01-13",
      "models": {
        "baseline": {
          "current_price": 1614.0999755859375,
          "predicted_price": 1639.060316904688,
          "predicted_change": 24.96034131875058,
          "predicted_change_pct": 1.5463937609992096,
          "predicted_direction": 1,
          "confidence": 0.5
        },
        "mslstm": {
          "current_price": 1614.0999755859375,
          "predicted_price": 1604.1163236752545,
          "predicted_change": -9.983651910682966,
          "predicted_change_pct": -0.6185274804343388,
          "predicted_direction": 0,
          "confidence": 0.5
        },
        "mslstma": {
          "current_price": 1614.0999755859375,
          "predicted_price": 1589.8572087420835,
          "predicted_change": -24.242766843854042,
          "predicted_change_pct": -1.5019371297031126,
          "predicted_direction": 0,
          "confidence": 0.5
        },
        "ensemble": {
          "current_price": 1614.0999755859375,
          "predicted_price": 1628.0423011556222,
          "predicted_change": 13.942325569684726,
          "predicted_change_pct": 0.8637832712080629,
          "predicted_direction": 1,
          "confidence": 0.4642921533603517
        }
      }
    },
    {
      "ticker": "ITC.NS",
      "prediction_date": "2026-01-12",
      "target_date": "2026-01-13",
      "models": {
        "baseline": {
          "current_price": 337.1499938964844,
          "predicted_price": 374.5406104529393,
          "predicted_change": 37.390616556454916,
          "predicted_change_pct": 11.090202353061596,
          "predicted_direction": 1,
          "confidence": 0.5
        },
        "mslstm": {
          "current_price": 337.1499938964844,
          "predicted_price": 364.0713169121882,
          "predicted_change": 26.92132301570382,
          "predicted_change_pct": 7.984969154105781,
          "predicted_direction": 1,
          "confidence": 0.5
        },
        "mslstma": {
          "current_price": 337.1499938964844,
          "predicted_price": 360.3484549194691,
          "predicted_change": 23.198461022984702,
          "predicted_change_pct": 6.880753801854533,
          "predicted_direction": 1,
          "confidence": 0.5
        },
        "ensemble": {
          "current_price": 337.1499938964844,
          "predicted_price": 341.5176550629135,
          "predicted_change": 4.367661166429116,
          "predicted_change_pct": 1.295465296010101,
          "predicted_direction": 1,
          "confidence": 0.20866175773602968
        }
      }
    },
    {
      "ticker": "JSWSTEEL.NS",
      "prediction_date": "2026-01-12",
      "target_date": "2026-01-13",
      "models": {
        "baseline": {
          "current_price": 1158.800048828125,
          "predicted_price": 1141.06235854164,
          "predicted_change": -17.737690286485076,
          "predicted_change_pct": -1.5306946443800151,
          "predicted_direction": 0,
          "confidence": 0.5
        },
        "mslstm": {
          "current_price": 1158.800048828125,
          "predicted_price": 1113.0386210555662,
          "predicted_change": -45.76142777255882,
          "predicted_change_pct": -3.949035713179039,
          "predicted_direction": 0,
          "confidence": 0.5
        },
        "mslstma": {
          "current_price": 1158.800048828125,
          "predicted_price": 1090.3164653985368,
          "predicted_change": -68.48358342958818,
          "predicted_change_pct": -5.909870602684597,
          "predicted_direction": 0,
          "confidence": 0.5
        },
        "ensemble": {
          "current_price": 1158.800048828125,
          "predicted_price": 1168.296856915747,
          "predicted_change": 9.496808087621957,
          "predicted_change_pct": 0.8195381159351811,
          "predicted_direction": 1,
          "confidence": 0.25186754777754783
        }
      }
    },
    {
      "ticker": "KOTAKBANK.NS",
      "prediction_date": "2026-01-12",
      "target_date": "2026-01-13",
      "models": {
        "baseline": {
          "current_price": 2126.800048828125,
          "predicted_price": 2238.3108871310833,
          "predicted_change": 111.51083830295829,
          "predicted_change_pct": 5.243127503424749,
          "predicted_direction": 1,
          "confidence": 0.5
        },
        "mslstm": {
          "current_price": 2126.800048828125,
          "predicted_price": 2173.2330902875983,
          "predicted_change": 46.433041459473316,
          "predicted_change_pct": 2.183234925401578,
          "predicted_direction": 1,
          "confidence": 0.5
        },
        "mslstma": {
          "current_price": 2126.800048828125,
          "predicted_price": 2159.4881940652267,
          "predicted_change": 32.68814523710171,
          "predicted_change_pct": 1.536963724216256,
          "predicted_direction": 1,
          "confidence": 0.5
        },
        "ensemble": {
          "current_price": 2126.800048828125,
          "predicted_price": 2140.6600791613614,
          "predicted_change": 13.86003033323641,
          "predicted_change_pct": 0.6516846913217522,
          "predicted_direction": 1,
          "confidence": 0.6172230211433569
        }
      }
    },
    {
      "ticker": "LT.NS",
      "prediction_date": "2026-01-12",
      "target_date": "2026-01-13",
      "models": {
        "baseline": {
          "current_price": 4025.199951171875,
          "predicted_price": 3662.1103278653172,
          "predicted_change": -363.08962330655777,
          "predicted_change_pct": -9.02041209656802,
          "predicted_direction": 0,
          "confidence": 0.5
        },
        "mslstm": {
          "current_price": 4025.199951171875,
          "predicted_price": 3738.204643083678,
          "predicted_change": -286.9953080881969,
          "predicted_change_pct": -7.129964015940193,
          "predicted_direction": 0,
          "confidence": 0.5
        },
        "mslstma": {
          "current_price": 4025.199951171875,
          "predicted_price": 3709.8249534018687,
          "predicted_change": -315.3749977700063,
          "predicted_change_pct": -7.835014448864575,
          "predicted_direction": 0,
          "confidence": 0.5
        },
        "ensemble": {
          "current_price": 4025.199951171875,
          "predicted_price": 4023.2397473792494,
          "predicted_change": -1.9602037926256344,
          "predicted_change_pct": -0.048698296144389364,
          "predicted_direction": 0,
          "confidence": 0.03940804236130502
        }
      }
    },
    {
      "ticker": "M&M.NS",
      "prediction_date": "2026-01-12",
      "target_date": "2026-01-13",
      "models": {
        "baseline": {
          "current_price": 3677.300048828125,
          "predicted_price": 3414.2657124740363,
          "predicted_change": -263.03433635408874,
          "predicted_change_pct": -7.152920155044518,
          "predicted_direction": 0,
          "confidence": 0.5
        },
        "mslstm": {
          "current_price": 3677.300048828125,
          "predicted_price": 3273.888242879635,
          "predicted_change": -403.4118059484899,
          "predicted_change_pct": -10.970326070537773,
          "predicted_direction": 0,
          "confidence": 0.5
        },
        "mslstma": {
          "current_price": 3677.300048828125,
          "predicted_price": 3261.6534405664424,
          "predicted_change": -415.64660826168256,
          "predicted_change_pct": -11.30303762931012,
          "predicted_direction": 0,
          "confidence": 0.5
        },
        "ensemble": {
          "current_price": 3677.300048828125,
          "predicted_price": 3696.4598730712314,
          "predicted_change": 19.159824243106414,
          "predicted_change_pct": 0.5210296681994242,
          "predicted_direction": 1,
          "confidence": 0.31156527975378023
        }
      }
    },
    {
      "ticker": "MARUTI.NS",
      "prediction_date": "2026-01-12",
      "target_date": "2026-01-13",
      "models": {
        "baseline": {
          "current_price": 16501.0,
          "predicted_price": 14358.60236261948,
          "predicted_change": -2142.39763738052,
          "predicted_change_pct": -12.983441230110415,
          "predicted_direction": 0,
          "confidence": 0.5
        },
        "mslstm": {
          "current_price": 16501.0,
          "predicted_price": 15802.783334752196,
          "predicted_change": -698.2166652478045,
          "predicted_change_pct": -4.231359706974147,
          "predicted_direction": 0,
          "confidence": 0.5
        },
        "mslstma": {
          "current_price": 16501.0,
          "predicted_price": 15306.124963695067,
          "predicted_change": -1194.875036304933,
          "predicted_change_pct": -7.241228024392054,
          "predicted_direction": 0,
          "confidence": 0.5
        },
        "ensemble": {
          "current_price": 16501.0,
          "predicted_price": 16525.031819110456,
          "predicted_change": 24.031819110456127,
          "predicted_change_pct": 0.1456385619686973,
          "predicted_direction": 1,
          "confidence": 0.0756634284701807
        }
      }
    },
    {
      "ticker": "NESTLEIND.NS",
      "prediction_date": "2026-01-12",
      "target_date": "2026-01-13",
      "models": {
        "baseline": {
          "current_price": 1299.0999755859375,
          "predicted_price": 1292.3571756832825,
          "predicted_change": -6.742799902654951,
          "predicted_change_pct": -0.5190362581304564,
          "predicted_direction": 0,
          "confidence": 0.5
        },
        "mslstm": {
          "current_price": 1299.0999755859375,
          "predicted_price": 1264.8127137510164,
          "predicted_change": -34.28726183492108,
          "predicted_change_pct": -2.6393089430593153,
          "predicted_direction": 0,
          "confidence": 0.5
        },
        "mslstma": {
          "current_price": 1299.0999755859375,
          "predicted_price": 1270.8359303529141,
          "predicted_change": -28.264045233023353,
          "predicted_change_pct": -2.175663595119026,
          "predicted_direction": 0,
          "confidence": 0.5
        },
        "ensemble": {
          "current_price": 1299.0999755859375,
          "predicted_price": 1292.742950924279,
          "predicted_change": -6.357024661658443,
          "predicted_change_pct": -0.4893406805578038,
          "predicted_direction": 0,
          "confidence": 0.19986720734157015
        }
      }
    },
    {
      "ticker": "NTPC.NS",
      "prediction_date": "2026-01-12",
      "target_date": "2026-01-13",
      "models": {
        "baseline": {
          "current_price": 336.0,
          "predicted_price": 337.03534337177547,
          "predicted_change": 1.0353433717754683,
          "predicted_change_pct": 0.30813790826651477,
          "predicted_direction": 1,
          "confidence": 0.5
        },
        "mslstm": {
          "current_price": 336.0,
          "predicted_price": 346.3597695796779,
          "predicted_change": 10.359769579677902,
          "predicted_change_pct": 3.0832647558565185,
          "predicted_direction": 1,
          "confidence": 0.5
        },
        "mslstma": {
          "current_price": 336.0,
          "predicted_price": 344.3930926742477,
          "predicted_change": 8.393092674247725,
          "predicted_change_pct": 2.49794424828802,
          "predicted_direction": 1,
          "confidence": 0.5
        },
        "ensemble": {
          "current_price": 336.0,
          "predicted_price": 336.1824402857386,
          "predicted_change": 0.1824402857386076,
          "predicted_change_pct": 0.05429770408886814,
          "predicted_direction": 1,
          "confidence": 0.017338660220251878
        }
      }
    },
    {
      "ticker": "ONGC.NS",
      "prediction_date": "2026-01-12",
      "target_date": "2026-01-13",
      "models": {
        "baseline": {
          "current_price": 234.08999633789062,
          "predicted_price": 227.62828624435403,
          "predicted_change": -6.461710093536595,
          "predicted_change_pct": -2.7603529388798065,
          "predicted_direction": 0,
          "confidence": 0.5
        },
        "mslstm": {
          "current_price": 234.08999633789062,
          "predicted_price": 230.0833126880943,
          "predicted_change": -4.006683649796315,
          "predicted_change_pct": -1.711599689212251,
          "predicted_direction": 0,
          "confidence": 0.5
        },
        "mslstma": {
          "current_price": 234.08999633789062,
          "predicted_price": 230.3215764749875,
          "predicted_change": -3.76841986290313,
          "predicted_change_pct": -1.6098167037705058,
          "predicted_direction": 0,
          "confidence": 0.5
        },
        "ensemble": {
          "current_price": 234.08999633789062,
          "predicted_price": 232.4965472784721,
          "predicted_change": -1.593449059418532,
          "predicted_change_pct": -0.6806993397182604,
          "predicted_direction": 0,
          "confidence": 0.43771960053958014
        }
      }
    },
    {
      "ticker": "POWERGRID.NS",
      "prediction_date": "2026-01-12",
      "target_date": "2026-01-13",
      "models": {
        "baseline": {
          "current_price": 258.0,
          "predicted_price": 281.3479414424764,
          "predicted_change": 23.347941442476383,
          "predicted_change_pct": 9.049589706386186,
          "predicted_direction": 1,
          "confidence": 0.5
        },
        "mslstm": {
          "current_price": 258.0,
          "predicted_price": 275.64707778441874,
          "predicted_change": 17.64707778441874,
          "predicted_change_pct": 6.839952629619672,
          "predicted_direction": 1,
          "confidence": 0.5
        },
        "mslstma": {
          "current_price": 258.0,
          "predicted_price": 274.78857346441504,
          "predicted_change": 16.788573464415038,
          "predicted_change_pct": 6.507199017215126,
          "predicted_direction": 1,
          "confidence": 0.5
        },
        "ensemble": {
          "current_price": 258.0,
          "predicted_price": 259.6837516503529,
          "predicted_change": 1.6837516503529173,
          "predicted_change_pct": 0.6526169187414332,
          "predicted_direction": 1,
          "confidence": 0.4621503912341802
        }
      }
    },
    {
      "ticker": "RELIANCE.NS",
      "prediction_date": "2026-01-12",
      "target_date": "2026-01-13",
      "models": {
        "baseline": {
          "current_price": 1475.300048828125,
          "predicted_price": 1494.2820892849995,
          "predicted_change": 18.98204045687453,
          "predicted_change_pct": 1.2866562616840271,
          "predicted_direction": 1,
          "confidence": 0.5
        },
        "mslstm": {
          "current_price": 1475.300048828125,
          "predicted_price": 1460.4637440853185,
          "predicted_change": -14.836304742806533,
          "predicted_change_pct": -1.005646597422094,
          "predicted_direction": 0,
          "confidence": 0.5
        },
        "mslstma": {
          "current_price": 1475.300048828125,
          "predicted_price": 1462.0862212944412,
          "predicted_change": -13.213827533683798,
          "predicted_change_pct": -0.8956705142238675,
          "predicted_direction": 0,
          "confidence": 0.5
        },
        "ensemble": {
          "current_price": 1475.300048828125,
          "predicted_price": 1465.1935512627267,
          "predicted_change": -10.106497565398286,
          "predicted_change_pct": -0.6850469213653287,
          "predicted_direction": 0,
          "confidence": 0.39019618015875035
        }
      }
    },
    {
      "ticker": "SBIN.NS",
      "prediction_date": "2026-01-12",
      "target_date": "2026-01-13",
      "models": {
        "baseline": {
          "current_price": 1000.5,
          "predicted_price": 864.9688003191186,
          "predicted_change": -135.5311996808814,
          "predicted_change_pct": -13.5463467946908,
          "predicted_direction": 0,
          "confidence": 0.5
        },
        "mslstm": {
          "current_price": 1000.5,
          "predicted_price": 903.7188242046104,
          "predicted_change": -96.78117579538957,
          "predicted_change_pct": -9.673280939069418,
          "predicted_direction": 0,
          "confidence": 0.5
        },
        "mslstma": {
          "current_price": 1000.5,
          "predicted_price": 919.6658058115136,
          "predicted_change": -80.83419418848644,
          "predicted_change_pct": -8.079379728984149,
          "predicted_direction": 0,
          "confidence": 0.5
        },
        "ensemble": {
          "current_price": 1000.5,
          "predicted_price": 1000.4849347297223,
          "predicted_change": -0.015065270277659693,
          "predicted_change_pct": -0.0015057741406976355,
          "predicted_direction": 0,
          "confidence": 0.0008568869927785272
        }
      }
    },
    {
      "ticker": "SUNPHARMA.NS",
      "prediction_date": "2026-01-12",
      "target_date": "2026-01-13",
      "models": {
        "baseline": {
          "current_price": 1729.9000244140625,
          "predicted_price": 1761.93841792093,
          "predicted_change": 32.03839350686758,
          "predicted_change_pct": 1.8520372885548309,
          "predicted_direction": 1,
          "confidence": 0.5
        },
        "mslstm": {
          "current_price": 1729.9000244140625,
          "predicted_price": 1753.4729541314955,
          "predicted_change": 23.572929717433,
          "predicted_change_pct": 1.3626758416526163,
          "predicted_direction": 1,
          "confidence": 0.5
        },
        "mslstma": {
          "current_price": 1729.9000244140625,
          "predicted_price": 1774.676159860348,
          "predicted_change": 44.77613544628548,
          "predicted_change_pct": 2.58836550172612,
          "predicted_direction": 1,
          "confidence": 0.5
        },
        "ensemble": {
          "current_price": 1729.9000244140625,
          "predicted_price": 1712.4163307070673,
          "predicted_change": -17.483693706995155,
          "predicted_change_pct": -1.0106765396987072,
          "predicted_direction": 0,
          "confidence": 0.5426497381582269
        }
      }
    },
    {
      "ticker": "TATASTEEL.NS",
      "prediction_date": "2026-01-12",
      "target_date": "2026-01-13",
      "models": {
        "baseline": {
          "current_price": 178.39999389648438,
          "predicted_price": 172.93064531526306,
          "predicted_change": -5.469348581221311,
          "predicted_change_pct": -3.0657784575905733,
          "predicted_direction": 0,
          "confidence": 0.5
        },
        "mslstm": {
          "current_price": 178.39999389648438,
          "predicted_price": 173.2825963454693,
          "predicted_change": -5.117397551015074,
          "predicted_change_pct": -2.86849648323666,
          "predicted_direction": 0,
          "confidence": 0.5
        },
        "mslstma": {
          "current_price": 178.39999389648438,
          "predicted_price": 168.52441647508158,
          "predicted_change": -9.875577421402795,
          "predicted_change_pct": -5.535637757439071,
          "predicted_direction": 0,
          "confidence": 0.5
        },
        "ensemble": {
          "current_price": 178.39999389648438,
          "predicted_price": 178.81434330195233,
          "predicted_change": 0.4143494054679593,
          "predicted_change_pct": 0.23225864329814438,
          "predicted_direction": 1,
          "confidence": 0.05809568534588516
        }
      }
    },
    {
      "ticker": "TCS.NS",
      "prediction_date": "2026-01-12",
      "target_date": "2026-01-13",
      "models": {
        "baseline": {
          "current_price": 3207.800048828125,
          "predicted_price": 3185.1154774859783,
          "predicted_change": -22.684571342146683,
          "predicted_change_pct": -0.7071691189241669,
          "predicted_direction": 0,
          "confidence": 0.5
        },
        "mslstm": {
          "current_price": 3207.800048828125,
          "predicted_price": 3222.0763440990663,
          "predicted_change": 14.276295270941318,
          "predicted_change_pct": 0.4450494124830673,
          "predicted_direction": 1,
          "confidence": 0.5
        },
        "mslstma": {
          "current_price": 3207.800048828125,
          "predicted_price": 3194.191740763504,
          "predicted_change": -13.608308064620815,
          "predicted_change_pct": -0.4242255707176068,
          "predicted_direction": 0,
          "confidence": 0.5
        },
        "ensemble": {
          "current_price": 3207.800048828125,
          "predicted_price": 3231.662163305962,
          "predicted_change": 23.862114477837167,
          "predicted_change_pct": 0.7438778637887555,
          "predicted_direction": 1,
          "confidence": 0.49436908101031163
        }
      }
    },
    {
      "ticker": "TECHM.NS",
      "prediction_date": "2026-01-12",
      "target_date": "2026-01-13",
      "models": {
        "baseline": {
          "current_price": 1582.199951171875,
          "predicted_price": 1579.8869487346456,
          "predicted_change": -2.313002437229443,
          "predicted_change_pct": -0.146189009519071,
          "predicted_direction": 0,
          "confidence": 0.5
        },
        "mslstm": {
          "current_price": 1582.199951171875,
          "predicted_price": 1559.250750701256,
          "predicted_change": -22.949200470618962,
          "predicted_change_pct": -1.4504614573917385,
          "predicted_direction": 0,
          "confidence": 0.5
        },
        "mslstma": {
          "current_price": 1582.199951171875,
          "predicted_price": 1543.219255643351,
          "predicted_change": -38.98069552852394,
          "predicted_change_pct": -2.463702233061782,
          "predicted_direction": 0,
          "confidence": 0.5
        },
        "ensemble": {
          "current_price": 1582.199951171875,
          "predicted_price": 1578.6345911099318,
          "predicted_change": -3.565360061943238,
          "predicted_change_pct": -0.22534193982893802,
          "predicted_direction": 0,
          "confidence": 0.12105868085688665
        }
      }
    },
    {
      "ticker": "ULTRACEMCO.NS",
      "prediction_date": "2026-01-12",
      "target_date": "2026-01-13",
      "models": {
        "baseline": {
          "current_price": 11937.0,
          "predicted_price": 12118.81430886843,
          "predicted_change": 181.8143088684301,
          "predicted_change_pct": 1.5231155974569033,
          "predicted_direction": 1,
          "confidence": 0.5
        },
        "mslstm": {
          "current_price": 11937.0,
          "predicted_price": 11726.25233573909,
          "predicted_change": -210.74766426091082,
          "predicted_change_pct": -1.7654994073964203,
          "predicted_direction": 0,
          "confidence": 0.5
        },
        "mslstma": {
          "current_price": 11937.0,
          "predicted_price": 11785.121844889305,
          "predicted_change": -151.87815511069493,
          "predicted_change_pct": -1.2723310304992408,
          "predicted_direction": 0,
          "confidence": 0.5
        },
        "ensemble": {
          "current_price": 11937.0,
          "predicted_price": 12034.114120866283,
          "predicted_change": 97.11412086628297,
          "predicted_change_pct": 0.8135555069639144,
          "predicted_direction": 1,
          "confidence": 0.4323482003693011
        }
      }
    },
    {
      "ticker": "VEDL.NS",
      "prediction_date": "2026-01-12",
      "target_date": "2026-01-13",
      "models": {
        "baseline": {
          "current_price": 609.8499755859375,
          "predicted_price": 497.4890258362684,
          "predicted_change": -112.36094974966909,
          "predicted_change_pct": -18.424359145331415,
          "predicted_direction": 0,
          "confidence": 0.5
        },
        "mslstm": {
          "current_price": 609.8499755859375,
          "predicted_price": 520.7270087251909,
          "predicted_change": -89.1229668607466,
          "predicted_change_pct": -14.61391660713246,
          "predicted_direction": 0,
          "confidence": 0.5
        },
        "mslstma": {
          "current_price": 609.8499755859375,
          "predicted_price": 509.11838126476687,
          "predicted_change": -100.73159432117063,
          "predicted_change_pct": -16.51743844449428,
          "predicted_direction": 0,
          "confidence": 0.5
        },
        "ensemble": {
          "current_price": 609.8499755859375,
          "predicted_price": 592.3346416853,
          "predicted_change": -17.51533390063753,
          "predicted_change_pct": -2.8720725755230214,
          "predicted_direction": 0,
          "confidence": 0.4620913929789465
        }
      }
    },
    {
      "ticker": "WIPRO.NS",
      "prediction_date": "2026-01-12",
      "target_date": "2026-01-13",
      "models": {
        "baseline": {
          "current_price": 261.95001220703125,
          "predicted_price": 257.8327607796173,
          "predicted_change": -4.117251427413976,
          "predicted_change_pct": -1.5717698933183977,
          "predicted_direction": 0,
          "confidence": 0.5
        },
        "mslstm": {
          "current_price": 261.95001220703125,
          "predicted_price": 259.37471702729454,
          "predicted_change": -2.575295179736713,
          "predicted_change_pct": -0.9831246649079528,
          "predicted_direction": 0,
          "confidence": 0.5
        },
        "mslstma": {
          "current_price": 261.95001220703125,
          "predicted_price": 255.80247846602833,
          "predicted_change": -6.147533741002917,
          "predicted_change_pct": -2.3468346839183307,
          "predicted_direction": 0,
          "confidence": 0.5
        },
        "ensemble": {
          "current_price": 261.95001220703125,
          "predicted_price": 264.1625266423353,
          "predicted_change": 2.2125144353040582,
          "predicted_change_pct": 0.8446323085319785,
          "predicted_direction": 1,
          "confidence": 0.40722495011881255
        }
      }
    }
  ],
  "date": "2026-01-12"
}